cleanco/__init__.py
cleanco/classify.py
cleanco/clean.py
cleanco/clean_old.py
cleanco/cleanco.py
cleanco/termdata.py
cleanco-2.0.1.dist-info/LICENSE.txt
cleanco-2.0.1.dist-info/METADATA
cleanco-2.0.1.dist-info/WHEEL
cleanco-2.0.1.dist-info/top_level.txt
cleanco-2.0.1.dist-info/RECORD
