Metadata-Version: 2.1
Name: cleanco
Version: 2.0.1
Summary: Python library to process company names
Home-page: https://github.com/psolin/cleanco
Author: Paul Solin
Author-email: paul@paulsolin.com
License: MIT
Platform: UNKNOWN
Classifier: Topic :: Office/Business
Classifier: Development Status :: 4 - Beta
Classifier: Intended Audience :: Developers
Classifier: License :: OSI Approved :: MIT License
Classifier: Programming Language :: Python :: 3
